py_sat/__init__.py
py_sat/client.py
py_sat/constant.py
py_sat/exceptions.py
py_sat/http_client.py
py_sat/utils.py
py_sat/models/__init__.py
py_sat/models/account.py
py_sat/models/base.py
py_sat/models/error.py
py_sat/models/inquiry.py
py_sat/models/order.py
py_sat/models/ping.py
py_sat/models/product.py
py_sat/signature/__init__.py
py_sat/signature/interface.py
py_sat/signature/pss.py
py_sat_sdk-1.0.1.dist-info/METADATA
py_sat_sdk-1.0.1.dist-info/WHEEL
py_sat_sdk-1.0.1.dist-info/top_level.txt
py_sat_sdk-1.0.1.dist-info/RECORD
